{
    "os": "Linux-5.4.0-135-generic-x86_64-with-debian-buster-sid",
    "python": "3.7.15",
    "heartbeatAt": "2022-12-16T16:52:21.409002",
    "startedAt": "2022-12-16T16:52:20.700585",
    "docker": null,
    "cuda": null,
    "args": [],
    "state": "running",
    "program": "<python with no main file>",
    "git": {
        "remote": "https://github.com/jrsykes/Elodea.git",
        "commit": "f3dedaffeaf4952492c4853d5ba7c6584b5304a6"
    },
    "email": "jamie.sykes@york.ac.uk",
    "root": "/home/userfs/j/jrs596/scripts/Elodea",
    "host": "csgpu2.cs.york.ac.uk",
    "username": "jrs596",
    "executable": "/scratch/staff/jrs596/python_environments/envs/def_detr_pl/bin/python3",
    "cpu_count": 20,
    "cpu_count_logical": 40,
    "cpu_freq": {
        "current": 1747.2958249999997,
        "min": 800.0,
        "max": 3000.0
    },
    "cpu_freq_per_core": [
        {
            "current": 1500.081,
            "min": 800.0,
            "max": 3000.0
        },
        {
            "current": 2672.782,
            "min": 800.0,
            "max": 3000.0
        },
        {
            "current": 800.128,
            "min": 800.0,
            "max": 3000.0
        },
        {
            "current": 1500.01,
            "min": 800.0,
            "max": 3000.0
        },
        {
            "current": 805.649,
            "min": 800.0,
            "max": 3000.0
        },
        {
            "current": 2630.499,
            "min": 800.0,
            "max": 3000.0
        },
        {
            "current": 799.98,
            "min": 800.0,
            "max": 3000.0
        },
        {
            "current": 2631.957,
            "min": 800.0,
            "max": 3000.0
        },
        {
            "current": 799.61,
            "min": 800.0,
            "max": 3000.0
        },
        {
            "current": 2633.894,
            "min": 800.0,
            "max": 3000.0
        },
        {
            "current": 799.996,
            "min": 800.0,
            "max": 3000.0
        },
        {
            "current": 2532.741,
            "min": 800.0,
            "max": 3000.0
        },
        {
            "current": 2647.102,
            "min": 800.0,
            "max": 3000.0
        },
        {
            "current": 2646.659,
            "min": 800.0,
            "max": 3000.0
        },
        {
            "current": 800.006,
            "min": 800.0,
            "max": 3000.0
        },
        {
            "current": 2645.872,
            "min": 800.0,
            "max": 3000.0
        },
        {
            "current": 1366.4,
            "min": 800.0,
            "max": 3000.0
        },
        {
            "current": 800.005,
            "min": 800.0,
            "max": 3000.0
        },
        {
            "current": 800.375,
            "min": 800.0,
            "max": 3000.0
        },
        {
            "current": 2479.207,
            "min": 800.0,
            "max": 3000.0
        },
        {
            "current": 1501.983,
            "min": 800.0,
            "max": 3000.0
        },
        {
            "current": 2638.881,
            "min": 800.0,
            "max": 3000.0
        },
        {
            "current": 800.293,
            "min": 800.0,
            "max": 3000.0
        },
        {
            "current": 1499.772,
            "min": 800.0,
            "max": 3000.0
        },
        {
            "current": 800.749,
            "min": 800.0,
            "max": 3000.0
        },
        {
            "current": 2625.333,
            "min": 800.0,
            "max": 3000.0
        },
        {
            "current": 800.005,
            "min": 800.0,
            "max": 3000.0
        },
        {
            "current": 2582.096,
            "min": 800.0,
            "max": 3000.0
        },
        {
            "current": 800.003,
            "min": 800.0,
            "max": 3000.0
        },
        {
            "current": 2570.336,
            "min": 800.0,
            "max": 3000.0
        },
        {
            "current": 800.001,
            "min": 800.0,
            "max": 3000.0
        },
        {
            "current": 2635.881,
            "min": 800.0,
            "max": 3000.0
        },
        {
            "current": 2550.555,
            "min": 800.0,
            "max": 3000.0
        },
        {
            "current": 2689.212,
            "min": 800.0,
            "max": 3000.0
        },
        {
            "current": 799.982,
            "min": 800.0,
            "max": 3000.0
        },
        {
            "current": 2700.04,
            "min": 800.0,
            "max": 3000.0
        },
        {
            "current": 1303.533,
            "min": 800.0,
            "max": 3000.0
        },
        {
            "current": 800.637,
            "min": 800.0,
            "max": 3000.0
        },
        {
            "current": 800.011,
            "min": 800.0,
            "max": 3000.0
        },
        {
            "current": 2583.632,
            "min": 800.0,
            "max": 3000.0
        }
    ],
    "disk": {
        "total": 86.169921875,
        "used": 35.6976203918457
    },
    "gpu": "NVIDIA GeForce GTX 1080 Ti",
    "gpu_count": 8,
    "gpu_devices": [
        {
            "name": "NVIDIA GeForce GTX 1080 Ti",
            "memory_total": 11811160064
        },
        {
            "name": "NVIDIA GeForce GTX 1080 Ti",
            "memory_total": 11811160064
        },
        {
            "name": "NVIDIA GeForce GTX 1080 Ti",
            "memory_total": 11811160064
        },
        {
            "name": "NVIDIA GeForce GTX 1080 Ti",
            "memory_total": 11811160064
        },
        {
            "name": "NVIDIA GeForce GTX 1080 Ti",
            "memory_total": 11811160064
        },
        {
            "name": "NVIDIA GeForce GTX 1080 Ti",
            "memory_total": 11811160064
        },
        {
            "name": "NVIDIA GeForce GTX 1080 Ti",
            "memory_total": 11811160064
        },
        {
            "name": "NVIDIA GeForce GTX 1080 Ti",
            "memory_total": 11811160064
        }
    ],
    "memory": {
        "total": 187.5677032470703
    }
}
